{"hash":"d61d61ab0bb3d2a58858f945f616349da00620d7","data":{"data":{"exhibitor":{"assetVideo":{"__typename":"data_Asset","url":"https://media.graphcms.com/TihOtrlTRCTsa9Wmn9zQ"},"code":"dakawomina","delivery":["pickup"],"email":"dakawomina@yahoo.fr","facebook":"Projet-Dakawomina-136703219814874","image":{"url":"https://media.graphcms.com/cLI3N0v0QKOU0kpcbVKM"},"instagram":null,"name":"Dakawomina ASBL","payment":["banktransfer"],"phone":"+32 476 99 65 57","pickUpRelay":["Cortil Gerardine 1 bte 003, 1348 Louvain-la-Neuve"],"pictures":[{"url":"https://media.graphcms.com/VenD2uMcQ5WsHoA6hZlY"}],"presentation":"<p>L'Asbl DAKAWOMINA est active depuis 2012 dans la région de Mopti au centre du Mali pour soutenir des projets émanant des populations locales et visant à l'amélioration de leurs conditions de vie.</p>\n<p>Construction de structures médicales et scolaires, de latrines, creusement de puits, initiatives génératrices de revenus pour es femmes: embouche (engraissement de bétail), jardin potager, formations... N'hésitez pas à lire <a href=\"https://dakawominanews.naniepat.be\">les articles de notre blog</a> pour en savoir plus.</p>","products":[{"exhibitor":{"code":"dakawomina","name":"Dakawomina ASBL"},"id":"ckj1a3fqg0vmr0a52kji5dfbp","image":{"url":"https://media.graphcms.com/4cUk3CPHRDqtXffpwv8i"},"name":"Colliers maliens","price":20},{"exhibitor":{"code":"dakawomina","name":"Dakawomina ASBL"},"id":"ckj1amk081asa0a94vllc7nvl","image":{"url":"https://media.graphcms.com/wScoEC1jRrS6E4NO1lTl"},"name":"Calendrier Mali 2021","price":12},{"exhibitor":{"code":"dakawomina","name":"Dakawomina ASBL"},"id":"ckj1awb346pre0a06gwru5slt","image":{"url":"https://media.graphcms.com/bnnck9o2RnGEfvVeispZ"},"name":"Porte de grenier dogon","price":50},{"exhibitor":{"code":"dakawomina","name":"Dakawomina ASBL"},"id":"ckj1azzsw1gaq0b127g11d0v5","image":{"url":"https://media.graphcms.com/4dGY3b4TQG4YK93qMcyH"},"name":"Chapeau Pheul de Fatoma","price":35},{"exhibitor":{"code":"dakawomina","name":"Dakawomina ASBL"},"id":"ckj1b3pag14m90a52d8iezzm9","image":{"url":"https://media.graphcms.com/cKUaBbhaQtKpip4TYavg"},"name":"Pot à lait en bois (petit)","price":40},{"exhibitor":{"code":"dakawomina","name":"Dakawomina ASBL"},"id":"ckj1b53g01m5k0b522scby31p","image":{"url":"https://media.graphcms.com/4sAR0yTzTNatUh2oco6Y"},"name":"Pot à lait en bois (grand)","price":60},{"exhibitor":{"code":"dakawomina","name":"Dakawomina ASBL"},"id":"ckj1b6eig6tzg0a06t6ciejtz","image":{"url":"https://media.graphcms.com/n667vKBCSEq9YEZkvayo"},"name":"Pot à lait en bois (duo)","price":80},{"exhibitor":{"code":"dakawomina","name":"Dakawomina ASBL"},"id":"ckj1bbw1k1hi90a09eapgqk11","image":{"url":"https://media.graphcms.com/5R4ueIlTTBqPENR2f35g"},"name":"Porte gourde","price":12},{"exhibitor":{"code":"dakawomina","name":"Dakawomina ASBL"},"id":"ckj1bcrog16cb0a5234u67opi","image":{"url":"https://media.graphcms.com/zhhMr8oHTuWKNOayDGA9"},"name":"Paire de maniques","price":8},{"exhibitor":{"code":"dakawomina","name":"Dakawomina ASBL"},"id":"ckj1bdda86wzx0a06yqrgarm6","image":{"url":"https://media.graphcms.com/2zHlJztlT5inb7N6UFQC"},"name":"Masque","price":4},{"exhibitor":{"code":"dakawomina","name":"Dakawomina ASBL"},"id":"ckj1bef3c1pou0b52dcyv89ei","image":{"url":"https://media.graphcms.com/0JWcTQgXRv6sxUdQpglp"},"name":"Étui tablette","price":12},{"exhibitor":{"code":"dakawomina","name":"Dakawomina ASBL"},"id":"ckj1bfel417dm0a520d5v5xcq","image":{"url":"https://media.graphcms.com/5cRWPS5nQv2OsmNycvxE"},"name":"Boite (petite)","price":15},{"exhibitor":{"code":"dakawomina","name":"Dakawomina ASBL"},"id":"ckj1bfusg6x6a0a06w8k11y1y","image":{"url":"https://media.graphcms.com/0EL8dOPSQ9mth8dtBMgK"},"name":"Boite (grande)","price":18},{"exhibitor":{"code":"dakawomina","name":"Dakawomina ASBL"},"id":"ckj1c1qlk09610a1699mi0pzc","image":{"url":"https://media.graphcms.com/sfv3MovQEGJwJzPonSBy"},"name":"Bague","price":2},{"exhibitor":{"code":"dakawomina","name":"Dakawomina ASBL"},"id":"ckj1f7xpk298c0a94wiqntvqm","image":{"url":"https://media.graphcms.com/NzbuUaaSi6t9iHz20C9Q"},"name":"Collier Djenné (fin)","price":2},{"exhibitor":{"code":"dakawomina","name":"Dakawomina ASBL"},"id":"ckj1fahj40sdr0a16268ayzm7","image":{"url":"https://media.graphcms.com/OBb91Y0TsyXy2CPUia1E"},"name":"Collier Djenné (multicolore)","price":3},{"exhibitor":{"code":"dakawomina","name":"Dakawomina ASBL"},"id":"ckj1fd6r41zoz0a52g2zdb58s","image":{"url":"https://media.graphcms.com/iRayHu3KQa2pFdHeUnu0"},"name":"Collier Djenné (épais)","price":3},{"exhibitor":{"code":"dakawomina","name":"Dakawomina ASBL"},"id":"ckj1fp0og7zcx0a06ixmsrer1","image":{"url":"https://media.graphcms.com/tkz2iZNORKCb7gho2SDJ"},"name":"Bracelet Djenné (fin)","price":1},{"exhibitor":{"code":"dakawomina","name":"Dakawomina ASBL"},"id":"ckj1fttio2g390a94s3olhcmc","image":{"url":"https://media.graphcms.com/HT2xjTJXTxOXfJ4cLEht"},"name":"Bracelet Djenné (épais)","price":1.5},{"exhibitor":{"code":"dakawomina","name":"Dakawomina ASBL"},"id":"ckj1fufw8819t0a06p05cope1","image":{"url":"https://media.graphcms.com/9vaKGLzQSvebqmwuNuQu"},"name":"Bracelet Djenné (multicolore)","price":1.5},{"exhibitor":{"code":"dakawomina","name":"Dakawomina ASBL"},"id":"ckj1fvlk810nf0a16w2tatce3","image":{"url":"https://media.graphcms.com/95GLR6UISYqn6vOsxdwq"},"name":"Bracelet Djenné (enfant)","price":1},{"exhibitor":{"code":"dakawomina","name":"Dakawomina ASBL"},"id":"ckj1fw4uo81q50a0604acqf2c","image":{"url":"https://media.graphcms.com/A3l84f1NTFuj3yiBKK6I"},"name":"Collier Djenné (enfant)","price":1},{"exhibitor":{"code":"dakawomina","name":"Dakawomina ASBL"},"id":"ckj1fzqhc2lmn0b52r57hf1tf","image":{"url":"https://media.graphcms.com/rXlirzsS56HTDptMV0o4"},"name":"Coussin en Bogolan de Ségou","price":30},{"exhibitor":{"code":"dakawomina","name":"Dakawomina ASBL"},"id":"ckj1g22l42lth0b52p5iqy5ep","image":{"url":"https://media.graphcms.com/t6ObvH55RXmtHDnraHK5"},"name":"Pagne dogon en coton malien","price":25},{"exhibitor":{"code":"dakawomina","name":"Dakawomina ASBL"},"id":"ckj1g8ngw01vp0b555et11l9f","image":{"url":"https://media.graphcms.com/WwhWgLucRCSWcgO82gwB"},"name":"Livre d'Art - Perspectives","price":100},{"exhibitor":{"code":"dakawomina","name":"Dakawomina ASBL"},"id":"ckj1g9wzs2n5q0b52byjewotl","image":{"url":"https://media.graphcms.com/ORPKJYciRj6K8ICpVGsh"},"name":"Livre d'Art - La pêche de St Pierre en Port à Dakawomina","price":120},{"exhibitor":{"code":"dakawomina","name":"Dakawomina ASBL"},"id":"ckj1gateg2ns40b52388qhkzt","image":{"url":"https://media.graphcms.com/VHkf1WSZSTmVrE8LLgnb"},"name":"Livre d'Art - Mali, Pays de traditions","price":120},{"exhibitor":{"code":"dakawomina","name":"Dakawomina ASBL"},"id":"ckj1gbs4g03rj0b55s8facwit","image":{"url":"https://media.graphcms.com/i6BBOld6Qf2PdnjcMJX8"},"name":"Livre d'Art - Hommage","price":120},{"exhibitor":{"code":"dakawomina","name":"Dakawomina ASBL"},"id":"ckj1gglqg2ndx0a947fqzsvzt","image":{"url":"https://media.graphcms.com/1SH8esXgS76bo3JRQBd8"},"name":"Livre photos - Le Grand Défi du Mali","price":100},{"exhibitor":{"code":"dakawomina","name":"Dakawomina ASBL"},"id":"ckj1ghqmo17ox0a16jz5x9z5m","image":{"url":"https://media.graphcms.com/DoMUrzxVQvC9Pa5fpXM2"},"name":"Livre photos - MALI Des villes, des génies et des Hommes","price":80},{"exhibitor":{"code":"dakawomina","name":"Dakawomina ASBL"},"id":"ckj1giwao2t4i0b52g2ydmmri","image":{"url":"https://media.graphcms.com/oUCG4LscRMu8NXXO7Mo5"},"name":"Livre photos A3 - Il était une fois un FLEUVE","price":150},{"exhibitor":{"code":"dakawomina","name":"Dakawomina ASBL"},"id":"ckj1gjr5s2q8x0a949lktssnv","image":{"url":"https://media.graphcms.com/oUCG4LscRMu8NXXO7Mo5"},"name":"Livre photos A4 - Il était une fois un FLEUVE","price":100},{"exhibitor":{"code":"dakawomina","name":"Dakawomina ASBL"},"id":"ckj1gkp402ngb0a09946l37cx","image":{"url":"https://media.graphcms.com/ShfO7nnuQ1AKuVW9gwRc"},"name":"Livre photos A4 - Le fabuleux PAYS DOGON","price":100},{"exhibitor":{"code":"dakawomina","name":"Dakawomina ASBL"},"id":"ckj1gl0oo8bwk0a0627km471f","image":{"url":"https://media.graphcms.com/ShfO7nnuQ1AKuVW9gwRc"},"name":"Livre photos A3 - Le fabuleux PAYS DOGON","price":150},{"exhibitor":{"code":"dakawomina","name":"Dakawomina ASBL"},"id":"ckj1gxk2o0khs0b5548hi64n5","image":{"url":"https://media.graphcms.com/N99TSPB2QcWI3EL1MqYe"},"name":"Set de bracelets et colliers Djenné","price":18},{"exhibitor":{"code":"dakawomina","name":"Dakawomina ASBL"},"id":"ckj1gy11s0ktt0b55xgn030c1","image":{"url":"https://media.graphcms.com/pZ3iPgOERg6iTB6IE7s2"},"name":"Set de bracelets et colliers Djenné","price":15},{"exhibitor":{"code":"dakawomina","name":"Dakawomina ASBL"},"id":"ckj1gyh948n3q0a06szis3qju","image":{"url":"https://media.graphcms.com/beNr5r4CSyeLccR5St6p"},"name":"Set de colliers Djenné","price":15},{"exhibitor":{"code":"dakawomina","name":"Dakawomina ASBL"},"id":"ckj1gyvww8ne20a06kwciiqmg","image":{"url":"https://media.graphcms.com/ME2u4TnESIug1j5KTch1"},"name":"Set de colliers Djenné","price":12}],"promotion":"<p><i>NB : Merci de prendre préalablement RdV au 0476 996 557 pour l'enlèvement sur place (mesure Covid).</i></p>","store":[],"story":"<p>L'Asbl DAKAWOMINA est active depuis 2012 dans la région de Mopti au centre du Mali pour soutenir des projets émanant des populations locales et visant à l'amélioration de leurs conditions de vie.</p>\n<p>Construction de structures médicales et scolaires, de latrines, creusement de puits, initiatives génératrices de revenus pour es femmes: embouche (engraissement de bétail), jardin potager, formations... N'hésitez pas à lire <a href=\"https://dakawominanews.naniepat.be\">les articles de notre blog</a> pour en savoir plus.</p>\n<p>Hélas, depuis,2012, la situation géopolitique du Mali n'a cessé de se dégrader et le centre du pays est le théâtre de combats plongeant les populations dans la désolation.  En 2019 de nombreux villages ont fait l'objet de massacres avant d'être incendiés.  Les survivants, femmes, enfants et personnes âgées, ont quitté leurs villages pour se réfugier dans des camps de fortune organisés sur des terrains mis à leur disposition, souvent par des particuliers, aux abords des villes.</p>\n<p>Cette situation nous a amené à modifier nos priorités afin de répondre aux demandes d'aide alimentaire d'urgence des villageois.</p>\nLa ventes des articles de cette Vitrine de Noël nous permettra de poursuivre ces actions en faveur de ces populations.</p>\n\n<p><b>DON</b></p>\n<p>Vous pouvez aussi soutenir nos projets en faisant un don. Le numéro de compte de l'association est le <code>BE72 0016 7107 8816</code>.</p>","website":"https://www.projet-dakawomina.org"}}},"context":{"code":"dakawomina","locale":"fr-be","title":"Dakawomina ASBL"}}