{"hash":"d61d61ab0bb3d2a58858f945f616349da00620d7","data":{"data":{"product":{"description":"<p>Box composée de :</p>\n<ul>\n<li>un petit savon Tonic (savon pressé à froid, à la cire d'abeille, et aux extraits revigorants de romarin et citron),</li>\n<li>un petit Visage Wow (infusion de propolis pour hydrater et protéger la peau),</li>\n<li>un shampoing (tous types de cheveux, au Rhassoul marocain et à la cire d'abeille),</li>\n<li>un P'tit Beezou (baume protecteur pour lèvres au miel sauvage et propolis pour les empêcher de gercer).</li>\n</ul>\n<p>Habeebee est une savonnerie naturelle de Bruxelles proposant du parrainage de ruches et d'abeilles, ainsi que des formations concernant leur bien-être et leur préservation.</p>","exhibitor":{"code":"poll-n","name":"Poll'n"},"id":"ckipvak1k1b8d0b59psux8o0n","image":{"url":"https://media.graphcms.com/6SH4cvXRyyYSO5jmfs6t"},"name":"Box Cadeau Habeebee \"Bee Surprised\"","packaging":null,"pictures":[{"url":"https://media.graphcms.com/Ehzv07beQ3efXTPHitWC"},{"url":"https://media.graphcms.com/6SH4cvXRyyYSO5jmfs6t"}],"price":16.7}}},"context":{"id":"ckipvak1k1b8d0b59psux8o0n","locale":"nl-be","title":"Box Cadeau Habeebee \"Bee Surprised\" par Poll'n"}}