{"hash":"d61d61ab0bb3d2a58858f945f616349da00620d7","data":{"data":{"product":{"description":"<p>Un paquet de thé vert fair trade en vrac.</p>","exhibitor":{"code":"ccmes","name":"Cri du Cœur d'une Mère qui Espère ASBL"},"id":"ckij3ehhc0beb0b56v43ocpva","image":{"url":"https://media.graphcms.com/2OSwWy7QSqkuCvhrAhzT"},"name":"Thé vert fair trade","packaging":"Paquet 125 g","pictures":[],"price":5}}},"context":{"id":"ckij3ehhc0beb0b56v43ocpva","locale":"fr-be","title":"Thé vert fair trade par Cri du Cœur d'une Mère qui Espère ASBL"}}